temapy/__init__.py
temapy/gateway.py
temapy/sequences.py
temapy/examples/__init__.py
temapy/examples/average_as_new_sequence.py
temapy-1.0.0.dist-info/METADATA
temapy-1.0.0.dist-info/WHEEL
temapy-1.0.0.dist-info/top_level.txt
temapy-1.0.0.dist-info/RECORD
