Metadata-Version: 2.4
Name: temapy
Version: 1.0.0
Summary: Python interface for scripting with TEMA
Author-email: Image Systems <support@imagesystems.se>
License-Expression: Apache-2.0
Classifier: Programming Language :: Python :: 3.13
Classifier: Operating System :: Microsoft :: Windows
Requires-Python: >=3.9
Requires-Dist: py4j
